{
  "flowSegmentData": {
    "frc": "FRC4",
    "currentSpeed": 24,
    "freeFlowSpeed": 30,
    "currentTravelTime": 173,
    "freeFlowTravelTime": 138,
    "confidence": 1,
    "roadClosure": false,
    "coordinates": {
      "coordinate": [
        {
          "latitude": 10.757614824237029,
          "longitude": 106.67432380995581
        },
        {
          "latitude": 10.757777128085408,
          "longitude": 106.67451827010944
        },
        {
          "latitude": 10.75787231995179,
          "longitude": 106.67460812411144
        },
        {
          "latitude": 10.758206314705452,
          "longitude": 106.67492194256624
        },
        {
          "latitude": 10.758426260259652,
          "longitude": 106.6751284726605
        },
        {
          "latitude": 10.758580493792909,
          "longitude": 106.67527331194731
        },
        {
          "latitude": 10.758867468416641,
          "longitude": 106.67554153284885
        },
        {
          "latitude": 10.759142420317856,
          "longitude": 106.67578695497377
        },
        {
          "latitude": 10.759501776063527,
          "longitude": 106.67611016116012
        },
        {
          "latitude": 10.759533973131674,
          "longitude": 106.67613832435484
        },
        {
          "latitude": 10.7598893758343,
          "longitude": 106.6764561661231
        },
        {
          "latitude": 10.759968509696947,
          "longitude": 106.67652724466205
        },
        {
          "latitude": 10.76021661604318,
          "longitude": 106.67674986801035
        },
        {
          "latitude": 10.76049551928255,
          "longitude": 106.6770019956578
        },
        {
          "latitude": 10.760586757723484,
          "longitude": 106.67708514413727
        },
        {
          "latitude": 10.76081477135997,
          "longitude": 106.67731983742613
        },
        {
          "latitude": 10.760970321192167,
          "longitude": 106.67747808775806
        },
        {
          "latitude": 10.761031997625398,
          "longitude": 106.67754111966991
        },
        {
          "latitude": 10.761218426713953,
          "longitude": 106.67773021540552
        },
        {
          "latitude": 10.761473201969233,
          "longitude": 106.67796356758987
        },
        {
          "latitude": 10.76176824363284,
          "longitude": 106.67823312959592
        },
        {
          "latitude": 10.76184474196844,
          "longitude": 106.67830420813482
        },
        {
          "latitude": 10.762123643701536,
          "longitude": 106.6785697468274
        },
        {
          "latitude": 10.762311389629877,
          "longitude": 106.6787481137269
        },
        {
          "latitude": 10.762643979607976,
          "longitude": 106.67906059107725
        },
        {
          "latitude": 10.763204581047878,
          "longitude": 106.67960373840288
        },
        {
          "latitude": 10.763491551269874,
          "longitude": 106.6798853703495
        },
        {
          "latitude": 10.763584106313326,
          "longitude": 106.67997388324699
        },
        {
          "latitude": 10.763714210329887,
          "longitude": 106.68009726486173
        },
        {
          "latitude": 10.764391491407748,
          "longitude": 106.68074904165246
        },
        {
          "latitude": 10.764547039394166,
          "longitude": 106.68089522204383
        },
        {
          "latitude": 10.764647581485617,
          "longitude": 106.68099044046386
        },
        {
          "latitude": 10.765078075827091,
          "longitude": 106.68139947733874
        },
        {
          "latitude": 10.765213531551405,
          "longitude": 106.68152822337152
        }
      ]
    },
    "@version": "4"
  }
}