{
  "flowSegmentData": {
    "frc": "FRC3",
    "currentSpeed": 42,
    "freeFlowSpeed": 42,
    "currentTravelTime": 295,
    "freeFlowTravelTime": 295,
    "confidence": 1,
    "roadClosure": false,
    "coordinates": {
      "coordinate": [
        {
          "latitude": 10.806132038407627,
          "longitude": 106.63628472169773
        },
        {
          "latitude": 10.806173534077885,
          "longitude": 106.63628472169773
        },
        {
          "latitude": 10.80620976045205,
          "longitude": 106.63629276832478
        },
        {
          "latitude": 10.806244669499343,
          "longitude": 106.63631422599695
        },
        {
          "latitude": 10.806271509943322,
          "longitude": 106.6363397069826
        },
        {
          "latitude": 10.806318439548214,
          "longitude": 106.63638396343134
        },
        {
          "latitude": 10.806364051823806,
          "longitude": 106.63645370086573
        },
        {
          "latitude": 10.806907199634447,
          "longitude": 106.6376231439965
        },
        {
          "latitude": 10.807748059995378,
          "longitude": 106.639782322254
        },
        {
          "latitude": 10.807825781621354,
          "longitude": 106.63999287566168
        },
        {
          "latitude": 10.807896916651229,
          "longitude": 106.6401859947108
        },
        {
          "latitude": 10.807937094762478,
          "longitude": 106.64029060086244
        },
        {
          "latitude": 10.808205332916652,
          "longitude": 106.64100675066959
        },
        {
          "latitude": 10.808709616704233,
          "longitude": 106.64235724290887
        },
        {
          "latitude": 10.809335915405716,
          "longitude": 106.64396790942271
        },
        {
          "latitude": 10.809570560960912,
          "longitude": 106.6445942052278
        },
        {
          "latitude": 10.809621524304648,
          "longitude": 106.64473368009664
        },
        {
          "latitude": 10.809647047139107,
          "longitude": 106.64484096845723
        },
        {
          "latitude": 10.809661784516733,
          "longitude": 106.64494289239985
        },
        {
          "latitude": 10.809668453385717,
          "longitude": 106.64507700285066
        },
        {
          "latitude": 10.809657750262577,
          "longitude": 106.64530767282594
        },
        {
          "latitude": 10.809643012884772,
          "longitude": 106.64555175384635
        },
        {
          "latitude": 10.809626958198608,
          "longitude": 106.64574084958195
        },
        {
          "latitude": 10.809566609037308,
          "longitude": 106.6464556582846
        },
        {
          "latitude": 10.80955854052641,
          "longitude": 106.64652271350997
        },
        {
          "latitude": 10.8095102117883,
          "longitude": 106.64696796020655
        },
        {
          "latitude": 10.809441876421287,
          "longitude": 106.64784504255465
        },
        {
          "latitude": 10.809424422084048,
          "longitude": 106.64813472112826
        },
        {
          "latitude": 10.809413718952259,
          "longitude": 106.6483117469233
        },
        {
          "latitude": 10.809400298871033,
          "longitude": 106.64853973468968
        },
        {
          "latitude": 10.80934398392258,
          "longitude": 106.64912177404602
        },
        {
          "latitude": 10.809193728343134,
          "longitude": 106.64981646618105
        },
        {
          "latitude": 10.809122675952501,
          "longitude": 106.65011687359078
        },
        {
          "latitude": 10.809070395214034,
          "longitude": 106.65043337425459
        },
        {
          "latitude": 10.809028817612356,
          "longitude": 106.65093494734049
        },
        {
          "latitude": 10.809020749086994,
          "longitude": 106.65108649214989
        },
        {
          "latitude": 10.809004612035647,
          "longitude": 106.65142310938137
        },
        {
          "latitude": 10.808996625841575,
          "longitude": 106.65160281738537
        },
        {
          "latitude": 10.80895233127662,
          "longitude": 106.65258450588505
        },
        {
          "latitude": 10.808951013966022,
          "longitude": 106.65262205681125
        },
        {
          "latitude": 10.808940310817311,
          "longitude": 106.65283395132349
        },
        {
          "latitude": 10.80893891117477,
          "longitude": 106.65288357219026
        },
        {
          "latitude": 10.808925491072364,
          "longitude": 106.65317459186849
        },
        {
          "latitude": 10.808913470612012,
          "longitude": 106.65327517470655
        },
        {
          "latitude": 10.808870575677648,
          "longitude": 106.65365738949129
        },
        {
          "latitude": 10.808802157833,
          "longitude": 106.65431453070005
        },
        {
          "latitude": 10.808780669192661,
          "longitude": 106.65450496754016
        },
        {
          "latitude": 10.808764614460378,
          "longitude": 106.65460823258724
        },
        {
          "latitude": 10.808732422661254,
          "longitude": 106.6546994276938
        },
        {
          "latitude": 10.808705582437316,
          "longitude": 106.65476916512819
        },
        {
          "latitude": 10.808672073320048,
          "longitude": 106.65482415041299
        },
        {
          "latitude": 10.808654618938075,
          "longitude": 106.6548509725032
        },
        {
          "latitude": 10.808619710171055,
          "longitude": 106.65490059336997
        },
        {
          "latitude": 10.808595586893372,
          "longitude": 106.65492607435561
        },
        {
          "latitude": 10.808540589106261,
          "longitude": 106.65498374184943
        },
        {
          "latitude": 10.808511114240199,
          "longitude": 106.65500654062606
        },
        {
          "latitude": 10.808458833395157,
          "longitude": 106.65504006823875
        },
        {
          "latitude": 10.808407869853996,
          "longitude": 106.65506286701537
        },
        {
          "latitude": 10.808340769217153,
          "longitude": 106.65507896026946
        },
        {
          "latitude": 10.808081999381407,
          "longitude": 106.65506286701537
        },
        {
          "latitude": 10.806978252549577,
          "longitude": 106.65497167190887
        },
        {
          "latitude": 10.806858870469366,
          "longitude": 106.65495289644576
        },
        {
          "latitude": 10.806716682233287,
          "longitude": 106.65493009766914
        },
        {
          "latitude": 10.806468614234527,
          "longitude": 106.65489657005645
        },
        {
          "latitude": 10.806384140982747,
          "longitude": 106.65489657005645
        },
        {
          "latitude": 10.806345197652965,
          "longitude": 106.654905957788
        },
        {
          "latitude": 10.806313087926972,
          "longitude": 106.65492205104209
        },
        {
          "latitude": 10.806204408828847,
          "longitude": 106.65500654062606
        },
        {
          "latitude": 10.806168182454087,
          "longitude": 106.65505616149284
        },
        {
          "latitude": 10.806133355730566,
          "longitude": 106.65510846456863
        },
        {
          "latitude": 10.806077040169106,
          "longitude": 106.65523184618337
        },
        {
          "latitude": 10.805975112269307,
          "longitude": 106.6554625161587
        },
        {
          "latitude": 10.805674679994942,
          "longitude": 106.65638251385099
        },
        {
          "latitude": 10.805603626771271,
          "longitude": 106.65666951021569
        },
        {
          "latitude": 10.805528539221156,
          "longitude": 106.65694443663978
        },
        {
          "latitude": 10.805496347074918,
          "longitude": 106.65706379494094
        },
        {
          "latitude": 10.805445383030783,
          "longitude": 106.6573883422318
        },
        {
          "latitude": 10.805390384666453,
          "longitude": 106.65787248095916
        },
        {
          "latitude": 10.805305911111223,
          "longitude": 106.65856449088511
        },
        {
          "latitude": 10.805241526767576,
          "longitude": 106.65882064184615
        },
        {
          "latitude": 10.805213368904539,
          "longitude": 106.6589212246842
        },
        {
          "latitude": 10.805127495639178,
          "longitude": 106.65923638424351
        },
        {
          "latitude": 10.805034953377495,
          "longitude": 106.65954886159386
        },
        {
          "latitude": 10.80499740953363,
          "longitude": 106.65967492541756
        },
        {
          "latitude": 10.804983989254996,
          "longitude": 106.6597178407618
        },
        {
          "latitude": 10.804828462178278,
          "longitude": 106.66013760647274
        },
        {
          "latitude": 10.804697058613895,
          "longitude": 106.66045410713656
        },
        {
          "latitude": 10.804461009585372,
          "longitude": 106.66103078207493
        },
        {
          "latitude": 10.804430134655105,
          "longitude": 106.6610790618372
        },
        {
          "latitude": 10.80432820619614,
          "longitude": 106.66127083978182
        },
        {
          "latitude": 10.804207505730696,
          "longitude": 106.66147066435343
        },
        {
          "latitude": 10.804117680182237,
          "longitude": 106.66158331713211
        },
        {
          "latitude": 10.803638912025757,
          "longitude": 106.66218681416058
        },
        {
          "latitude": 10.803051462866371,
          "longitude": 106.66291101059477
        },
        {
          "latitude": 10.802836901611448,
          "longitude": 106.66316850266026
        },
        {
          "latitude": 10.802759096360269,
          "longitude": 106.66325165113972
        },
        {
          "latitude": 10.80267997375082,
          "longitude": 106.66333614072374
        },
        {
          "latitude": 10.802603568131062,
          "longitude": 106.6633991726356
        },
        {
          "latitude": 10.802541900219031,
          "longitude": 106.6634434290844
        },
        {
          "latitude": 10.802505673402338,
          "longitude": 106.66346354565201
        }
      ]
    },
    "@version": "4"
  }
}